dfpwm/__init__.py
dfpwm/constants.py
dfpwm/convertor.pyi
dfpwm/convertor.pyx
dfpwm/resample.py
dfpwm/convertor.c
dfpwm/convertor.cpython-311-x86_64-linux-gnu.so
dfpwm-0.2.0.dist-info/LICENSE
dfpwm-0.2.0.dist-info/METADATA
dfpwm-0.2.0.dist-info/WHEEL
dfpwm-0.2.0.dist-info/RECORD
