Metadata-Version: 2.1
Name: dfpwm
Version: 0.2.0
Summary: DFPWM convertor for Python
License: MIT
Author: cyan
Author-email: contact@cyans.me
Requires-Python: >=3.9,<4.0
Classifier: License :: OSI Approved :: MIT License
Classifier: Programming Language :: Python :: 3
Classifier: Programming Language :: Python :: 3.9
Classifier: Programming Language :: Python :: 3.10
Classifier: Programming Language :: Python :: 3.11
Classifier: Programming Language :: Python :: 3.12
Classifier: Programming Language :: Python :: 3.13
Provides-Extra: resample
Requires-Dist: librosa (>=0.10.0,<0.11.0) ; extra == "resample"
Requires-Dist: numpy (>=2.0.0,<3.0.0)
